{"index.md":"c1b48b18","other_docker_nginx.md":"4c39a051","other_index.md":"3374e502","other_代码脱敏.md":"7cd00a3d","other_前端技术规范.md":"547cda1a","other_前端规范是什么.md":"6d9b7869","other_命名规范.md":"4a51b379","recommend_index.md":"36991415","recommend_technology_stack.md":"ceb95faf","guid_readme.md":"9337a817","basic_component.md":"28ce0226","basic_index.md":"cc1af871","basic_mock.md":"c8115f72","basic_request.md":"0f0a7f7c","basic_style.md":"6f9084b1","basic_svg.md":"a75139de","basic_version.md":"de8f1832","guid_index.md":"fcaa6b31","standard_index.md":"10a1a094","standard_comments.md":"4ed4f95d","standard_doc.md":"88936664","standard_format.md":"90bb7852","standard_git.md":"b00cc824","standard_name.md":"9cb38542","standard_structure.md":"f40d106a","vite-plugins_pages_layouts.md":"e4aa2d16","vite-plugins_常见插件介绍.md":"db3411ca","recommend_vscode.md":"82e0c4fb","standard_code.md":"18ef246b","standard_css.md":"c3d78916","从 0 搭建 vite 3 _ vue 3 前端工程化项目.md":"44635db6","standard_ignore.md":"4a6cae9d","standard_javascript.md":"a560fab5"}
